affo_user_service/__init__.py
affo_user_service/application.py
affo_user_service/cli.py
affo_user_service/extensions.py
affo_user_service/settings.py
affo_user_service/utils.py
affo_user_service/wsgi.py
affo_user_service/api/__init__.py
affo_user_service/api/auth.py
affo_user_service/api/exception.py
affo_user_service/api/password.py
affo_user_service/api/role.py
affo_user_service/api/user.py
affo_user_service/api/utils.py
affo_user_service/api/verification.py
affo_user_service/migrations/README
affo_user_service/migrations/alembic.ini
affo_user_service/migrations/env.py
affo_user_service/migrations/script.py.mako
affo_user_service/migrations/versions/0611f55803e6_.py
affo_user_service/models/__init__.py
affo_user_service/models/user.py
affo_user_service/spec/openapi.yaml
affo_user_service/verification/__init__.py
affo_user_service/verification/exception.py
affo_user_service/verification/generators.py
affo_user_service/verification/services.py
affo_user_service/verification/backends/__init__.py
affo_user_service/verification/backends/base.py
affo_user_service/verification/backends/dummy.py
affo_user_service/verification/backends/sms.py
affo_user_service-1.0.4.dist-info/LICENSE
affo_user_service-1.0.4.dist-info/METADATA
affo_user_service-1.0.4.dist-info/WHEEL
affo_user_service-1.0.4.dist-info/entry_points.txt
affo_user_service-1.0.4.dist-info/top_level.txt
affo_user_service-1.0.4.dist-info/RECORD
